LICENSE
MANIFEST.in
README.md
requirements.txt
setup.py
prwlr/__init__.py
prwlr/apis.py
prwlr/core.py
prwlr/databases.py
prwlr/errors.py
prwlr/network.py
prwlr/profiles.py
prwlr/stats.py
prwlr/utils.py
prwlr.egg-info/PKG-INFO
prwlr.egg-info/SOURCES.txt
prwlr.egg-info/dependency_links.txt
prwlr.egg-info/requires.txt
prwlr.egg-info/top_level.txt