Metadata-Version: 1.2
Name: prwlr
Version: 0.0.2
Summary: Annotate genetic interactions networks with phylogenetic profiles and other attributes.
Home-page: https://github.com/dizak/prwlr
Author: Dariusz Izak IBB PAS
Author-email: dariusz.izak@ibb.waw.pl
License: BSD
Keywords: genetic,interactions,network,phylogenetic,profile,module,pathway,kegg,evolution
Platform: UNKNOWN
Classifier: License :: OSI Approved :: BSD License
Classifier: Operating System :: POSIX :: Linux
Classifier: Programming Language :: Python :: 2
Classifier: Programming Language :: Python :: 3
Requires-Python: >=2.7, !=3.0.*, !=3.1.*, !=3.2.*, <4
